qmock/__init__.py
qmock/_python_compat.py
qmock/_qmock.py
qmock-1.0.0.dist-info/LICENSE
qmock-1.0.0.dist-info/METADATA
qmock-1.0.0.dist-info/WHEEL
qmock-1.0.0.dist-info/top_level.txt
qmock-1.0.0.dist-info/RECORD
